{"name":"Visualizar Parte Boletim caminho feliz","testSteps":[{"number":1,"description":"Dado que eu possuo uma Parte Boletim de posicao 1 e descricao \"descricao\" ja criada","duration":56,"startTime":1495484003129,"result":"SUCCESS"},{"number":2,"description":"Quando eu requisitar que esta Parte Boletim seja apresentada","duration":21,"startTime":1495484003185,"result":"SUCCESS"},{"number":3,"description":"Entao devo receber uma confirmação de \"sucesso\" na visualizacao","duration":1,"startTime":1495484003206,"result":"SUCCESS"}],"userStory":{"id":"visualizar-parte-boletim","storyName":"Visualizar Parte Boletim","path":"parteBoletim/visualizacao/visualizar_parte_boletim.feature","type":"feature"},"featureTag":{"name":"Visualizar Parte Boletim","type":"feature"},"title":"Visualizar Parte Boletim caminho feliz","description":"","startTime":1495484003102,"duration":105,"manual":false,"testSource":"Cucumber","result":"SUCCESS"}