{"name":"Visualizar Tipo de Documento caminho feliz","testSteps":[{"number":1,"description":"Dado que eu possuo um Tipo de Documento de nome \"lala\" ja criado","duration":41,"startTime":1495484011828,"result":"SUCCESS"},{"number":2,"description":"Quando eu requisitar que este Tipo de Documento seja apresentado","duration":11,"startTime":1495484011869,"result":"SUCCESS"},{"number":3,"description":"Entao devo receber uma confirmação de \"sucesso\" na visualizacao","duration":1,"startTime":1495484011880,"result":"SUCCESS"}],"userStory":{"id":"visualizar-tipo-de-documento","storyName":"Visualizar Tipo de Documento","path":"tipoDocumento/visualizacao/visualizar_tipo_documento.feature","type":"feature"},"featureTag":{"name":"Visualizar Tipo de Documento","type":"feature"},"title":"Visualizar Tipo de Documento caminho feliz","description":"","startTime":1495484011787,"duration":94,"manual":false,"testSource":"Cucumber","result":"SUCCESS"}