{"name":"Criar Assunto Geral falha nome obrigatorio","testSteps":[{"number":1,"description":"Dado que eu precise criar um Assunto Geral de secao x e nome nulo","duration":36,"startTime":1495483988414,"result":"SUCCESS"},{"number":2,"description":"Quando eu requisitar que este Assunto Geral seja criado","duration":52,"startTime":1495483988450,"result":"SUCCESS"},{"number":3,"description":"Entao devo receber uma confirmação de \"erro\" no cadastro","duration":2,"startTime":1495483988502,"result":"SUCCESS"}],"userStory":{"id":"criar-assunto-geral","storyName":"Criar Assunto Geral","path":"assuntoGeral/cadastro/cadastrar_assunto_geral.feature","type":"feature"},"featureTag":{"name":"Criar Assunto Geral","type":"feature"},"title":"Criar Assunto Geral falha nome obrigatorio","description":"","startTime":1495483988410,"duration":94,"manual":false,"testSource":"Cucumber","result":"SUCCESS"}