{"name":"Criar Categoria","testSteps":[{"number":1,"description":"Dado que eu precise criar uma Categoria de nome \"nome\" e descricao \"\"","duration":0,"startTime":1495483995787,"result":"SUCCESS"},{"number":2,"description":"Quando eu requisitar que esta Categoria seja criada","duration":32,"startTime":1495483995787,"result":"SUCCESS"},{"number":3,"description":"Entao devo receber uma confirmação de \"erro\" no cadastro","duration":2,"startTime":1495483995819,"result":"SUCCESS"}],"userStory":{"id":"criar-categoria","storyName":"Criar Categoria","path":"categoria/cadastro/cadastrar_categoria.feature","type":"feature"},"featureTag":{"name":"Criar Categoria","type":"feature"},"title":"Criar Categoria","description":"","startTime":1495483995704,"duration":117,"manual":false,"testSource":"Cucumber","result":"SUCCESS"}